odoo/addons/account_payment_order_tier_validation/README.rst
odoo/addons/account_payment_order_tier_validation/__init__.py
odoo/addons/account_payment_order_tier_validation/__manifest__.py
odoo/addons/account_payment_order_tier_validation/i18n/account_payment_order_tier_validation.pot
odoo/addons/account_payment_order_tier_validation/models/__init__.py
odoo/addons/account_payment_order_tier_validation/models/account_payment_order.py
odoo/addons/account_payment_order_tier_validation/models/tier_definition.py
odoo/addons/account_payment_order_tier_validation/readme/CONFIGURE.rst
odoo/addons/account_payment_order_tier_validation/readme/CONTRIBUTORS.rst
odoo/addons/account_payment_order_tier_validation/readme/DESCRIPTION.rst
odoo/addons/account_payment_order_tier_validation/readme/INSTALL.rst
odoo/addons/account_payment_order_tier_validation/readme/USAGE.rst
odoo/addons/account_payment_order_tier_validation/static/description/icon.png
odoo/addons/account_payment_order_tier_validation/static/description/index.html
odoo/addons/account_payment_order_tier_validation/tests/__init__.py
odoo/addons/account_payment_order_tier_validation/tests/test_payment_order_tier_validation.py
odoo/addons/account_payment_order_tier_validation/views/account_payment_order.xml
odoo12_addon_account_payment_order_tier_validation-12.0.1.0.0.99.dev3.dist-info/METADATA
odoo12_addon_account_payment_order_tier_validation-12.0.1.0.0.99.dev3.dist-info/WHEEL
odoo12_addon_account_payment_order_tier_validation-12.0.1.0.0.99.dev3.dist-info/top_level.txt
odoo12_addon_account_payment_order_tier_validation-12.0.1.0.0.99.dev3.dist-info/RECORD
